simp13/__init__.py
simp13/test.py
simp13/dl/__init__.py
simp13/dl/cv/__init__.py
simp13/dl/cv/detector.py
simp13-1.1.0.dist-info/METADATA
simp13-1.1.0.dist-info/WHEEL
simp13-1.1.0.dist-info/entry_points.txt
simp13-1.1.0.dist-info/top_level.txt
simp13-1.1.0.dist-info/RECORD
