Metadata-Version: 2.1
Name: simp13
Version: 1.1.0
Summary: Simple Utils Of simp13.com
Home-page: https://simp13.com
Author: Si Thu Phyo
Author-email: createcodes155@gmail.com
License: MIT
Platform: UNKNOWN
Classifier: License :: OSI Approved :: MIT License
Classifier: Programming Language :: Python :: 3
Requires-Dist: imutils
Requires-Dist: six
Requires-Dist: numpy
Requires-Dist: opencv-contrib-python
Requires-Dist: progressbar2
